{"type":"PR","pr":{"number":240,"head":"ebaa70de465e8d1d05319efb4c41f8fd4a3bdebc"},"user":"Kyle","status":"draft","branch":"cms/about","collection":"pages","title":"About","description":"If you work on open source software for Arm platforms, Linaro Connect is the place to be to understand the latest developments and work directly with the most active engineers and maintainers in the ecosystem.","objects":{"entry":{"path":"_pages/about.md","sha":"5f1de50d29d63f8b52d92faf89f3fb418d651f06"},"files":[]},"timeStamp":"2019-08-14T15:11:23.944Z"}