{
  "items": [
    { "name": "96Boards" },
    { "name": "AI/ML" },
    { "name": "Android Ecosystem" },
    { "name": "Arm on Arm" },
    { "name": "Automation & CI" },
    { "name": "Automotive" },
    { "name": "Big Data" },
    { "name": "Boot Architecture" },
    { "name": "Builds & Baselines" },
    { "name": "Data Center" },
    { "name": "Demo" },
    { "name": "Embedded" },
    { "name": "Enterprise" },
    { "name": "HPC" },
    { "name": "Industrial" },
    { "name": "IoT and Embedded" },
    { "name": "IoT Fog/Gateway/Edge Computing" },
    { "name": "LAVA" },
    { "name": "Linux Kernel" },
    { "name": "Neoverse Hyperscalers" },
    { "name": "Open Source Development" },
    { "name": "OS Build & Test" },
    { "name": "Power Management" },
    { "name": "Security" },
    { "name": "Testing & CI" },
    { "name": "Toolchain" },
    { "name": "Tools" },
    { "name": "Training" },
    { "name": "Trusted Substrate" },
    { "name": "Validation" },
    { "name": "Virtualization" },
    { "name": "None/Other" }
  ]
}
